nonebot_plugin_profile_settings/__init__.py
nonebot_plugin_profile_settings-0.1.1.dist-info/METADATA
nonebot_plugin_profile_settings-0.1.1.dist-info/WHEEL
nonebot_plugin_profile_settings-0.1.1.dist-info/RECORD
