Metadata-Version: 2.1
Name: nonebot_plugin_profile_settings
Version: 0.1.1
Summary: NoneBot2 插件用于设置机器人的头像和个人签名
License: MIT
Author: Endless-Path
Author-email: rk.chensiyu@gmail.com
Requires-Python: >=3.8,<4.0
Classifier: License :: OSI Approved :: MIT License
Classifier: Programming Language :: Python :: 3
Classifier: Programming Language :: Python :: 3.8
Classifier: Programming Language :: Python :: 3.9
Classifier: Programming Language :: Python :: 3.10
Classifier: Programming Language :: Python :: 3.11
Classifier: Programming Language :: Python :: 3.12
Classifier: Programming Language :: Python :: 3.13
Requires-Dist: nonebot-adapter-onebot (>=2.2.0,<3.0.0)
Requires-Dist: nonebot2 (>=2.0.0,<3.0.0)
